{
    "@class": "com.kony.gen.viz.model.component.KVizImage2",
    "DNDConfig": null,
    "_base64_": null,
    "_height_": {
        "type": "string",
        "value": "100%"
    },
    "_left_": {
        "type": "string",
        "value": "0dp"
    },
    "_margin_": [
        0,
        0,
        0,
        0
    ],
    "_padding_": [
        0,
        0,
        0,
        0
    ],
    "_skin_": "sb77f2f2b6c145ed8bd489f529b7c810",
    "_src_": "google.png",
    "_width_": {
        "type": "string",
        "value": "30dp"
    },
    "canUpdateUI": true,
    "centery": {
        "type": "string",
        "value": "50%"
    },
    "containerweight": 100,
    "id": "imgGoogle",
    "imagescalemode": 1,
    "info": null,
    "invokedProperty": "src",
    "iscustomlayout": false,
    "isvisible": true,
    "kuid": "j509d243ef874ade932b0e0b4a6970d3",
    "name": "kony.ui.Image2",
    "parent": "flxLoginWithGoogle",
    "pf": "frmLogin",
    "retaincontentalignment": false,
    "retainflexpositionproperties": false,
    "srcType": 1,
    "wType": "Image",
    "widgetalignment": 5,
    "zindex": 1
}